AUTHORS.txt
CHANGES.txt
LICENSE.txt
MANIFEST.in
README.txt
TODO.txt
setup.cfg
setup.py
docs/1to2.rst
docs/admin_client.rst
docs/architecture.rst
docs/client.rst
docs/index.rst
docs/job.rst
docs/library.rst
docs/worker.rst
gearman/__init__.py
gearman/admin_client.py
gearman/admin_client_handler.py
gearman/client.py
gearman/client_handler.py
gearman/command_handler.py
gearman/compat.py
gearman/connection.py
gearman/connection_manager.py
gearman/constants.py
gearman/errors.py
gearman/job.py
gearman/protocol.py
gearman/util.py
gearman/worker.py
gearman/worker_handler.py
gearman.egg-info/PKG-INFO
gearman.egg-info/SOURCES.txt
gearman.egg-info/dependency_links.txt
gearman.egg-info/top_level.txt